setup.py
phoenix_ml4/Framework.py
phoenix_ml4.egg-info/PKG-INFO
phoenix_ml4.egg-info/SOURCES.txt
phoenix_ml4.egg-info/dependency_links.txt
phoenix_ml4.egg-info/not-zip-safe
phoenix_ml4.egg-info/top_level.txt